jmpy/__init__.py
jmpy/cmdline.py
jmpy/encrypt_py.py
jmpy/log.py
jmpy4-1.1.3.dist-info/LICENSE
jmpy4-1.1.3.dist-info/METADATA
jmpy4-1.1.3.dist-info/WHEEL
jmpy4-1.1.3.dist-info/entry_points.txt
jmpy4-1.1.3.dist-info/top_level.txt
jmpy4-1.1.3.dist-info/RECORD
