Metadata-Version: 2.1
Name: jmpy4
Version: 1.1.3
Summary: python代码一键加密
Home-page: https://github.com/shenny520/jmpy-plus.git
Author: Shenny
Author-email: shenny520@outlook.com
License: MIT
Classifier: Programming Language :: Python :: 3
License-File: LICENSE
Requires-Dist: Cython ==3.0.0
